{"name":"b_work_with_campaign","testCaseName":"com.frolova.features.TestStory","testSteps":[{"number":1,"description":"Open site","duration":5377,"startTime":1431607254452,"result":"SUCCESS"},{"number":2,"description":"Fill first step","duration":1163,"startTime":1431607259832,"result":"SUCCESS"},{"number":3,"description":"Fill twot step","duration":1600,"startTime":1431607260998,"result":"SUCCESS"},{"number":4,"description":"Fill threet step","duration":7027,"startTime":1431607262601,"result":"SUCCESS"}],"userStory":{"id":"com.frolova.features.TestStory","storyName":"Test story","storyClassName":"com.frolova.features.TestStory","path":"com.frolova.features","type":"story"},"title":"B work with campaign","tags":[{"name":"Test story","type":"story"}],"startTime":1431607254417,"duration":15220,"driver":"chrome","manual":false,"result":"SUCCESS"}